jupyter_cjk_xelatex.py
setup.py
./console/__init__.py
console/__init__.py
jupyter_cjk_xelatex.egg-info/PKG-INFO
jupyter_cjk_xelatex.egg-info/SOURCES.txt
jupyter_cjk_xelatex.egg-info/dependency_links.txt
jupyter_cjk_xelatex.egg-info/entry_points.txt
jupyter_cjk_xelatex.egg-info/requires.txt
jupyter_cjk_xelatex.egg-info/top_level.txt