Metadata-Version: 1.0
Name: jupyter-cjk-xelatex
Version: 0.2
Summary: Handle the encoding error for jupyter nbconvert to convert notebook to pdf document
Home-page: https://github.com/rainx/jupyter-cjk-xelatex
Author: rainx
Author-email: i@rainx.cn
License: MIT
Keywords: jupyter pdf latex xelatex
Platform: UNKNOWN
